latex_proj_tool/__init__.py
latex_proj_tool/__main__.py
latex_proj_tool/logger.py
latex_proj_tool/tools.py
latex_proj_tool-0.1.dev4.dist-info/LICENSE
latex_proj_tool-0.1.dev4.dist-info/METADATA
latex_proj_tool-0.1.dev4.dist-info/WHEEL
latex_proj_tool-0.1.dev4.dist-info/top_level.txt
latex_proj_tool-0.1.dev4.dist-info/RECORD
