Metadata-Version: 2.1
Name: latex-proj-tool
Version: 0.1.dev4
Summary: A toolset to traverse and manipulate a Latex project with multiple .tex files.
Home-page: https://github.com/comaniac
Author: Cody Yu
Author-email: comaniac0422@gmail.com
License: Apache-2.0
Platform: UNKNOWN
Classifier: Development Status :: 3 - Alpha
Classifier: Intended Audience :: Developers
Classifier: Topic :: Software Development :: Build Tools
Classifier: License :: OSI Approved :: Apache Software License
Classifier: Programming Language :: Python :: 3
Classifier: Programming Language :: Python :: 3.6
Requires-Dist: argparse
